odoo/addons/partner_multiline_street2/LICENSE
odoo/addons/partner_multiline_street2/README.rst
odoo/addons/partner_multiline_street2/__init__.py
odoo/addons/partner_multiline_street2/__manifest__.py
odoo/addons/partner_multiline_street2/images/screen.png
odoo/addons/partner_multiline_street2/models/__init__.py
odoo/addons/partner_multiline_street2/models/res_partner.py
odoo/addons/partner_multiline_street2/models/res_users.py
odoo/addons/partner_multiline_street2/readme/CONTRIBUTORS.md
odoo/addons/partner_multiline_street2/readme/DESCRIPTION.md
odoo/addons/partner_multiline_street2/readme/USAGE.md
odoo/addons/partner_multiline_street2/static/description/icon.png
odoo/addons/partner_multiline_street2/static/description/index.html
odoo/addons/partner_multiline_street2/tests/TEST_INSTRUCTIONS.rst
odoo_addon_partner_multiline_street2-18.0.1.0.0.dist-info/METADATA
odoo_addon_partner_multiline_street2-18.0.1.0.0.dist-info/WHEEL
odoo_addon_partner_multiline_street2-18.0.1.0.0.dist-info/top_level.txt
odoo_addon_partner_multiline_street2-18.0.1.0.0.dist-info/RECORD
